pymoos.cpython-38-aarch64-linux-gnu.so
pymoos-2022.1.dist-info/top_level.txt
pymoos-2022.1.dist-info/WHEEL
pymoos-2022.1.dist-info/LICENSE
pymoos-2022.1.dist-info/METADATA
pymoos-2022.1.dist-info/RECORD
