Metadata-Version: 2.1
Name: pymoos
Version: 2022.1
Summary: MOOS Python Wrapper.
Home-page: https://github.com/russkel/python-moos
Author: Mohamed Saad Ibn Seddik <ms.ibnseddik@gmail.com>
Maintainer: Russ Webber <russ@rw.id.au>
License-File: LICENSE
Provides-Extra: test
Requires-Dist: pytest ; extra == 'test'
